fms_robot_plugin/__init__.py
fms_robot_plugin/constants.py
fms_robot_plugin/mqtt.py
fms_robot_plugin/robot.py
fms_robot_plugin/typings.py
fms_robot_plugin-1.1.1.dist-info/WHEEL
fms_robot_plugin-1.1.1.dist-info/METADATA
fms_robot_plugin-1.1.1.dist-info/RECORD
