Metadata-Version: 2.1
Name: fms-robot-plugin
Version: 1.1.1
Summary: 
Author: Dionesius Agung
Author-email: dionesius@movel.ai
Requires-Python: >=3.10,<4.0
Classifier: Programming Language :: Python :: 3
Classifier: Programming Language :: Python :: 3.10
Classifier: Programming Language :: Python :: 3.11
Requires-Dist: paho-mqtt (>=1.6.1,<2.0.0)
Requires-Dist: pydantic (>=2.3.0,<3.0.0)
Requires-Dist: requests (>=2.31.0,<3.0.0)
